string_treatment/__init__.py
string_treatment-2.0.0.dist-info/WHEEL
string_treatment-2.0.0.dist-info/METADATA
string_treatment-2.0.0.dist-info/RECORD
