Metadata-Version: 2.3
Name: string-treatment
Version: 2.0.0
Summary: For cleaning and adjusting words with inconsistency.
Author: Guilherme Huther
Author-email: Guilherme Huther <guilhermehuther@gmail.com>
License: Copyright (c) 2018 The Python Packaging Authority
Requires-Dist: mapply>=0.1.30
Requires-Dist: nltk>=3.9.1
Requires-Dist: pandas>=2.3.2
Requires-Dist: pyvis>=0.3.2
Requires-Dist: rapidfuzz>=3.14.1
Requires-Dist: tqdm>=4.67.1
Requires-Dist: unidecode>=1.4.0
Requires-Python: >=3.10
